{
    "Orkney & Shetland": {
        "date": "Wednesday 12 June",
        "last_issued": "Pollen forecast last issued: 05:43 (UTC+1) on Tue 11 Jun 2024",
        "pollen_levels": {
            "Today": "Low pollen",
            "Thu": "Low pollen",
            "Fri": "Low pollen",
            "Sat": "Low pollen"
        }
    },
    "Highlands & Eilean Siar": {
        "date": "Wednesday 12 June",
        "last_issued": "Pollen forecast last issued: 05:43 (UTC+1) on Tue 11 Jun 2024",
        "pollen_levels": {
            "Today": "Low pollen",
            "Thu": "Low pollen",
            "Fri": "Low pollen",
            "Sat": "Low pollen"
        }
    },
    "Grampian": {
        "date": "Wednesday 12 June",
        "last_issued": "Pollen forecast last issued: 05:43 (UTC+1) on Tue 11 Jun 2024",
        "pollen_levels": {
            "Today": "Low pollen",
            "Thu": "Low pollen",
            "Fri": "Low pollen",
            "Sat": "Low pollen"
        }
    },
    "Central, Tayside & Fife": {
        "date": "Wednesday 12 June",
        "last_issued": "Pollen forecast last issued: 05:43 (UTC+1) on Tue 11 Jun 2024",
        "pollen_levels": {
            "Today": "Low pollen",
            "Thu": "Low pollen",
            "Fri": "Low pollen",
            "Sat": "Low pollen"
        }
    },
    "Strathclyde": {
        "date": "Wednesday 12 June",
        "last_issued": "Pollen forecast last issued: 05:43 (UTC+1) on Tue 11 Jun 2024",
        "pollen_levels": {
            "Today": "Low pollen",
            "Thu": "Low pollen",
            "Fri": "Low pollen",
            "Sat": "Low pollen"
        }
    },
    "Dumfries, Galloway, Lothian & Borders": {
        "date": "Wednesday 12 June",
        "last_issued": "Pollen forecast last issued: 05:43 (UTC+1) on Tue 11 Jun 2024",
        "pollen_levels": {
            "Today": "Low pollen",
            "Thu": "Low pollen",
            "Fri": "Low pollen",
            "Sat": "Low pollen"
        }
    },
    "North East England": {
        "date": "Wednesday 12 June",
        "last_issued": "Pollen forecast last issued: 05:43 (UTC+1) on Tue 11 Jun 2024",
        "pollen_levels": {
            "Today": "Moderate pollen",
            "Thu": "Moderate pollen",
            "Fri": "Moderate pollen",
            "Sat": "Moderate pollen"
        }
    },
    "Northern Ireland": {
        "date": "Wednesday 12 June",
        "last_issued": "Pollen forecast last issued: 05:43 (UTC+1) on Tue 11 Jun 2024",
        "pollen_levels": {
            "Today": "Moderate pollen",
            "Thu": "Low pollen",
            "Fri": "Moderate pollen",
            "Sat": "Moderate pollen"
        }
    },
    "Yorkshire & Humber": {
        "date": "Wednesday 12 June",
        "last_issued": "Pollen forecast last issued: 05:43 (UTC+1) on Tue 11 Jun 2024",
        "pollen_levels": {
            "Today": "High pollen",
            "Thu": "Moderate pollen",
            "Fri": "Moderate pollen",
            "Sat": "Moderate pollen"
        }
    },
    "North West England": {
        "date": "Wednesday 12 June",
        "last_issued": "Pollen forecast last issued: 05:43 (UTC+1) on Tue 11 Jun 2024",
        "pollen_levels": {
            "Today": "High pollen",
            "Thu": "Moderate pollen",
            "Fri": "Moderate pollen",
            "Sat": "Moderate pollen"
        }
    },
    "East Midlands": {
        "date": "Wednesday 12 June",
        "last_issued": "Pollen forecast last issued: 05:43 (UTC+1) on Tue 11 Jun 2024",
        "pollen_levels": {
            "Today": "Moderate pollen",
            "Thu": "Moderate pollen",
            "Fri": "Moderate pollen",
            "Sat": "Moderate pollen"
        }
    },
    "West Midlands": {
        "date": "Wednesday 12 June",
        "last_issued": "Pollen forecast last issued: 05:43 (UTC+1) on Tue 11 Jun 2024",
        "pollen_levels": {
            "Today": "High pollen",
            "Thu": "Moderate pollen",
            "Fri": "Moderate pollen",
            "Sat": "Moderate pollen"
        }
    },
    "Wales": {
        "date": "Wednesday 12 June",
        "last_issued": "Pollen forecast last issued: 05:43 (UTC+1) on Tue 11 Jun 2024",
        "pollen_levels": {
            "Today": "High pollen",
            "Thu": "Moderate pollen",
            "Fri": "Moderate pollen",
            "Sat": "Moderate pollen"
        }
    },
    "East of England": {
        "date": "Wednesday 12 June",
        "last_issued": "Pollen forecast last issued: 05:43 (UTC+1) on Tue 11 Jun 2024",
        "pollen_levels": {
            "Today": "Moderate pollen",
            "Thu": "High pollen",
            "Fri": "Moderate pollen",
            "Sat": "Moderate pollen"
        }
    },
    "London & South East England": {
        "date": "Wednesday 12 June",
        "last_issued": "Pollen forecast last issued: 05:43 (UTC+1) on Tue 11 Jun 2024",
        "pollen_levels": {
            "Today": "Moderate pollen",
            "Thu": "High pollen",
            "Fri": "High pollen",
            "Sat": "Moderate pollen"
        }
    },
    "South West England": {
        "date": "Wednesday 12 June",
        "last_issued": "Pollen forecast last issued: 05:43 (UTC+1) on Tue 11 Jun 2024",
        "pollen_levels": {
            "Today": "High pollen",
            "Thu": "Moderate pollen",
            "Fri": "Moderate pollen",
            "Sat": "Moderate pollen"
        }
    }
}
